__init__.py
test.py
examples/code_locked_view.py
examples/cycle_button.py
examples/modal_button.py
examples/modal_select.py
examples/user_hybrid_select.py
quickUI/__init__.py
quickUI/interface/__init__.py
quickUI/interface/interface.py
quickUI/item/__init__.py
quickUI/item/button/__init__.py
quickUI/item/button/cycleButton.py
quickUI/item/button/modalButton.py
quickUI/item/button/state.py
quickUI/item/modal/__init__.py
quickUI/item/modal/modal.py
quickUI/item/modal/modalSelectOption.py
quickUI/item/select/UserHybridSelect.py
quickUI/item/select/__init__.py
quickUI/item/select/modalSelect.py
quickUI/view/__init__.py
quickUI/view/confirmationView.py
quickUI/view/view.py
tests/__init__.py
tests/bot.py
tests/test.py
quickUI-1.0.1.dist-info/LICENSE
quickUI-1.0.1.dist-info/METADATA
quickUI-1.0.1.dist-info/WHEEL
quickUI-1.0.1.dist-info/top_level.txt
quickUI-1.0.1.dist-info/RECORD
