Metadata-Version: 2.1
Name: quickUI
Version: 1.0.1
Summary: A extension to the disnake library for easier UI usage.
Author-email: OscarVsp <oscar.van.slijpe@outlook.be>
License: MIT
Project-URL: Homepage, https://github.com/OscarVsp/quickUI
Project-URL: Bug Tracker, https://github.com/OscarVsp/quickUI/issues
Keywords: disnake,discord,discord api
Classifier: Programming Language :: Python :: 3.8
Classifier: Programming Language :: Python :: 3.9
Classifier: Programming Language :: Python :: 3.10
Classifier: Programming Language :: Python :: 3.11
Classifier: Natural Language :: English
Classifier: License :: OSI Approved :: MIT License
Classifier: Operating System :: OS Independent
Classifier: Topic :: Software Development :: Libraries
Classifier: Topic :: Software Development :: Libraries :: Python Modules
Classifier: Typing :: Typed
Requires-Python: >=3.8
License-File: LICENSE
Requires-Dist: disnake (==2.8.*)
